{
  "path": ".\\p9",
  "type": "com.dse.parser.object.ProjectNode",
  "children": [
    {
      "path": ".\\p9\\1942.cpp",
      "type": "com.dse.parser.object.CppFileNode",
      "last-modified": "02/12/2025 06:29:13",
      "children": [
        {
          "path": ".\\p9\\1942.cpp\\",
          "type": "com.dse.parser.object.UnspecifiedDeclaration"
        }
      ]
    },
    {
      "path": ".\\p9\\1955.cpp",
      "type": "com.dse.parser.object.CppFileNode",
      "last-modified": "02/12/2025 06:29:13",
      "children": [
        {
          "path": ".\\p9\\1955.cpp\\",
          "type": "com.dse.parser.object.UnspecifiedDeclaration"
        }
      ]
    },
    {
      "path": ".\\p9\\1975.cpp",
      "type": "com.dse.parser.object.CppFileNode",
      "last-modified": "02/12/2025 06:29:13",
      "children": [
        {
          "path": ".\\p9\\1975.cpp\\",
          "type": "com.dse.parser.object.UnspecifiedDeclaration"
        }
      ]
    },
    {
      "path": ".\\p9\\1982.cpp",
      "type": "com.dse.parser.object.CppFileNode",
      "last-modified": "02/12/2025 06:29:13",
      "children": [
        {
          "path": ".\\p9\\1982.cpp\\",
          "type": "com.dse.parser.object.UnspecifiedDeclaration"
        }
      ]
    }
  ]
}